dr_source/__init__.py
dr_source/api.py
dr_source/cli.py
dr_source/logging.py
dr_source/core/__init__.py
dr_source/core/codebase.py
dr_source/core/db.py
dr_source/core/knowledge_base.py
dr_source/core/scanner.py
dr_source/core/usage.py
dr_source/plugins/__init__.py
dr_source/plugins/dependency/__init__.py
dr_source/plugins/dependency/plugin.py
dr_source/plugins/java/__init__.py
dr_source/plugins/java/plugin.py
dr_source/plugins/java/taint_detector.py
dr_source/plugins/java/taint_visitor.py
dr_source/plugins/python/__init__.py
dr_source/plugins/python/plugin.py
dr_source/plugins/python/taint_visitor.py
dr_source/plugins/regex/plugin.py
dr_source/reports/__init__.py
dr_source/reports/ascii.py
dr_source/reports/sarif.py
dr_source-0.98.0.dist-info/licenses/LICENSE
dr_source-0.98.0.dist-info/METADATA
dr_source-0.98.0.dist-info/WHEEL
dr_source-0.98.0.dist-info/entry_points.txt
dr_source-0.98.0.dist-info/top_level.txt
dr_source-0.98.0.dist-info/RECORD
