Metadata-Version: 2.4
Name: dr_source
Version: 0.98.0
Summary: A plugin-driven, multi-language SAST.
Author: thesp0nge
License: MIT License
Requires-Python: >=3.9
License-File: LICENSE
Requires-Dist: click
Requires-Dist: pyyaml
Requires-Dist: platformdirs
Requires-Dist: javalang
Requires-Dist: tabulate
Requires-Dist: importlib-metadata; python_version < "3.10"
Requires-Dist: pip-audit
Requires-Dist: tree-sitter
Requires-Dist: tree-sitter-java
Requires-Dist: tqdm
Dynamic: license-file
